sandman/__init__.py
sandman/decorators.py
sandman/exception.py
sandman/sandman.py
sandman/sandmanctl.py
sandman/model/__init__.py
sandman/model/models.py
sandman/model/utils.py
sandman/static/css/bootstrap-theme.css
sandman/static/css/bootstrap-theme.css.map
sandman/static/css/bootstrap-theme.min.css
sandman/static/css/bootstrap.css
sandman/static/css/bootstrap.css.map
sandman/static/css/bootstrap.min.css
sandman/static/fonts/glyphicons-halflings-regular.eot
sandman/static/fonts/glyphicons-halflings-regular.svg
sandman/static/fonts/glyphicons-halflings-regular.ttf
sandman/static/fonts/glyphicons-halflings-regular.woff
sandman/static/js/bootstrap.js
sandman/static/js/bootstrap.min.js
sandman/templates/attribute.html
sandman/templates/base.html
sandman/templates/collection.html
sandman/templates/error.html
sandman/templates/index.html
sandman/templates/resource.html
sandman-0.9.8.dist-info/DESCRIPTION.rst
sandman-0.9.8.dist-info/entry_points.txt
sandman-0.9.8.dist-info/METADATA
sandman-0.9.8.dist-info/metadata.json
sandman-0.9.8.dist-info/RECORD
sandman-0.9.8.dist-info/top_level.txt
sandman-0.9.8.dist-info/WHEEL
