Metadata-Version: 2.0
Name: sandman
Version: 0.9.8
Summary: Automated REST APIs for existing database-driven systems
Home-page: http://github.com/jeffknupp/sandman/
Author: Jeff Knupp
Author-email: jeff@jeffknupp.com
License: Apache Software License
Platform: any
Classifier: Programming Language :: Python
Classifier: Programming Language :: Python :: 2
Classifier: Programming Language :: Python :: 3
Classifier: Development Status :: 4 - Beta
Classifier: Natural Language :: English
Classifier: Environment :: Web Environment
Classifier: Intended Audience :: Developers
Classifier: License :: OSI Approved :: Apache Software License
Classifier: Operating System :: OS Independent
Classifier: Topic :: Software Development :: Libraries :: Python Modules
Classifier: Topic :: Software Development :: Libraries :: Application Frameworks
Classifier: Topic :: Internet :: WWW/HTTP :: Dynamic Content
Requires-Dist: Flask (>=0.10.1)
Requires-Dist: Flask-SQLAlchemy (>=1.0)
Requires-Dist: SQLAlchemy (>=0.8.2)
Requires-Dist: Flask-Admin (>=1.0.6)
Requires-Dist: Flask-HTTPAuth (>=2.2.1)
Requires-Dist: docopt (>=0.6.1)
Requires-Dist: click
Provides-Extra: testing
Requires-Dist: pytest; extra == 'testing'
